{"chunk_definitions":[{"chunk_id":"cw6j7pa6m5n3p","chunk_label":"unnamed-chunk-1","document_id":"A8D75AB","expansion_state":0,"options":{"engine":null},"row":19,"row_count":1,"visible":true},{"chunk_id":"cmdsqgejud8o5","chunk_label":"unnamed-chunk-2","document_id":"A8D75AB","expansion_state":1,"options":{"engine":null},"row":125,"row_count":1,"visible":true},{"chunk_id":"c7bv8s19j13fv","chunk_label":"unnamed-chunk-3","document_id":"A8D75AB","expansion_state":1,"options":{"engine":"r","label":"unnamed-chunk-1"},"row":141,"row_count":1,"visible":true},{"chunk_id":"cq7i8o8z0cmf5","chunk_label":"unnamed-chunk-4","document_id":"A8D75AB","expansion_state":0,"options":{"engine":null},"row":161,"row_count":1,"visible":true},{"chunk_id":"cfo8q928zc1cj","chunk_label":"unnamed-chunk-5","document_id":"A8D75AB","expansion_state":0,"options":{"engine":null},"row":178,"row_count":1,"visible":true},{"chunk_id":"c28xmaqpoexwo","chunk_label":"unnamed-chunk-6","document_id":"A8D75AB","expansion_state":0,"options":{"engine":null},"row":186,"row_count":1,"visible":true}],"doc_write_time":1497110457}